{
  "split": "single",
  "objects": [
    {
      "rotation": 120.04657617390114,
      "material": "metal",
      "color": "yellow",
      "shape": "cylinder",
      "size": "large",
      "3d_coords": [
        -2.0557711124420166,
        2.0509731769561768,
        0.699999988079071
      ],
      "pixel_coords": [
        246,
        82,
        13.5758056640625
      ]
    }
  ],
  "image_filename": "CLEVR_single_000400.png",
  "image_index": 400,
  "relationships": {
    "right": [
      []
    ],
    "left": [
      []
    ],
    "behind": [
      []
    ],
    "front": [
      []
    ]
  },
  "directions": {
    "right": [
      0.6563112735748291,
      0.7544902563095093,
      -0.0
    ],
    "above": [
      0.0,
      0.0,
      1.0
    ],
    "left": [
      -0.6563112735748291,
      -0.7544902563095093,
      0.0
    ],
    "behind": [
      -0.754490315914154,
      0.6563112735748291,
      0.0
    ],
    "front": [
      0.754490315914154,
      -0.6563112735748291,
      -0.0
    ],
    "below": [
      -0.0,
      -0.0,
      -1.0
    ]
  }
}