{
  "split": "single",
  "objects": [
    {
      "rotation": 196.1925183142825,
      "material": "rubber",
      "color": "green",
      "shape": "cube",
      "size": "large",
      "3d_coords": [
        -1.7090637683868408,
        -0.25253748893737793,
        0.699999988079071
      ],
      "pixel_coords": [
        184,
        110,
        12.098980903625488
      ]
    }
  ],
  "image_filename": "CLEVR_single_000305.png",
  "image_index": 305,
  "relationships": {
    "right": [
      []
    ],
    "left": [
      []
    ],
    "behind": [
      []
    ],
    "front": [
      []
    ]
  },
  "directions": {
    "right": [
      0.6563112735748291,
      0.7544902563095093,
      -0.0
    ],
    "above": [
      0.0,
      0.0,
      1.0
    ],
    "left": [
      -0.6563112735748291,
      -0.7544902563095093,
      0.0
    ],
    "behind": [
      -0.754490315914154,
      0.6563112735748291,
      0.0
    ],
    "front": [
      0.754490315914154,
      -0.6563112735748291,
      -0.0
    ],
    "below": [
      -0.0,
      -0.0,
      -1.0
    ]
  }
}