{
  "split": "single",
  "objects": [
    {
      "rotation": 39.92653220281727,
      "material": "metal",
      "color": "yellow",
      "shape": "sphere",
      "size": "large",
      "3d_coords": [
        1.8456631898880005,
        -2.370565176010132,
        0.699999988079071
      ],
      "pixel_coords": [
        212,
        208,
        8.121944427490234
      ]
    }
  ],
  "image_filename": "CLEVR_single_000301.png",
  "image_index": 301,
  "relationships": {
    "right": [
      []
    ],
    "left": [
      []
    ],
    "behind": [
      []
    ],
    "front": [
      []
    ]
  },
  "directions": {
    "right": [
      0.6563112735748291,
      0.7544902563095093,
      -0.0
    ],
    "above": [
      0.0,
      0.0,
      1.0
    ],
    "left": [
      -0.6563112735748291,
      -0.7544902563095093,
      0.0
    ],
    "behind": [
      -0.754490315914154,
      0.6563112735748291,
      0.0
    ],
    "front": [
      0.754490315914154,
      -0.6563112735748291,
      -0.0
    ],
    "below": [
      -0.0,
      -0.0,
      -1.0
    ]
  }
}