{
  "num_objects": 1,
  "split": "single",
  "image_index": 238,
  "image_filename": "CLEVRTEX_single_000238.png",
  "ground_material": "poliigongroundmoss001",
  "directions": {
    "behind": [
      -0.7179822325706482,
      0.6960614919662476,
      0.0
    ],
    "front": [
      0.7179822325706482,
      -0.6960614919662476,
      -0.0
    ],
    "left": [
      -0.6960614919662476,
      -0.7179822325706482,
      0.0
    ],
    "right": [
      0.6960614919662476,
      0.7179822325706482,
      -0.0
    ],
    "above": [
      0.0,
      0.0,
      1.0
    ],
    "below": [
      -0.0,
      -0.0,
      -1.0
    ]
  },
  "objects": [
    {
      "shape": "cube",
      "rotation": 273.83194698109725,
      "size": "medium",
      "3d_coords": [
        -2.0281448364257812,
        0.6698039770126343,
        0.4242640733718872
      ],
      "pixel_coords": [
        201,
        109,
        12.644750595092773
      ],
      "index": 1,
      "color": "brown",
      "material": "poliigontilesonyxopaloblack001"
    }
  ],
  "relationships": {
    "behind": [
      []
    ],
    "front": [
      []
    ],
    "left": [
      []
    ],
    "right": [
      []
    ]
  },
  "mask_filename": "CLEVRTEX_single_000238_flat.png",
  "normal_filename": "CLEVRTEX_single_000238_normal_0001.png",
  "albedo_filename": "CLEVRTEX_single_000238_albedo_0001.png",
  "depth_filename": "CLEVRTEX_single_000238_depth_0001.png",
  "shadow_filename": "CLEVRTEX_single_000238_shadow_0001.png"
}