{
  "num_objects": 1,
  "split": "single",
  "image_index": 433,
  "image_filename": "CLEVRTEX_single_000433.png",
  "ground_material": "poliigonwoodflooringmahoganyafricansanded001",
  "directions": {
    "behind": [
      -0.7423573136329651,
      0.6700041890144348,
      0.0
    ],
    "front": [
      0.7423573136329651,
      -0.6700041890144348,
      -0.0
    ],
    "left": [
      -0.6700041890144348,
      -0.7423573136329651,
      0.0
    ],
    "right": [
      0.6700041890144348,
      0.7423573136329651,
      -0.0
    ],
    "above": [
      0.0,
      0.0,
      1.0
    ],
    "below": [
      -0.0,
      -0.0,
      -1.0
    ]
  },
  "objects": [
    {
      "shape": "cylinder",
      "rotation": 111.79753941656453,
      "size": "large",
      "3d_coords": [
        2.401641845703125,
        -0.3900889754295349,
        0.8999999761581421
      ],
      "pixel_coords": [
        315,
        172,
        9.259977340698242
      ],
      "index": 1,
      "color": "purple",
      "material": "poliigonroadcityworn001"
    }
  ],
  "relationships": {
    "behind": [
      []
    ],
    "front": [
      []
    ],
    "left": [
      []
    ],
    "right": [
      []
    ]
  },
  "mask_filename": "CLEVRTEX_single_000433_flat.png",
  "normal_filename": "CLEVRTEX_single_000433_normal_0001.png",
  "albedo_filename": "CLEVRTEX_single_000433_albedo_0001.png",
  "depth_filename": "CLEVRTEX_single_000433_depth_0001.png",
  "shadow_filename": "CLEVRTEX_single_000433_shadow_0001.png"
}