{
  "num_objects": 1,
  "split": "single",
  "image_index": 446,
  "image_filename": "CLEVRTEX_single_000446.png",
  "ground_material": "poliigonstonebricksbeige015",
  "directions": {
    "behind": [
      -0.7714774012565613,
      0.6362566351890564,
      0.0
    ],
    "front": [
      0.7714774012565613,
      -0.6362566351890564,
      -0.0
    ],
    "left": [
      -0.6362566947937012,
      -0.771477460861206,
      0.0
    ],
    "right": [
      0.6362566947937012,
      0.771477460861206,
      -0.0
    ],
    "above": [
      0.0,
      0.0,
      1.0
    ],
    "below": [
      -0.0,
      -0.0,
      -1.0
    ]
  },
  "objects": [
    {
      "shape": "monkey",
      "rotation": 297.24128796187864,
      "size": "small",
      "3d_coords": [
        -1.5428591966629028,
        -2.85199236869812,
        0.4000000059604645
      ],
      "pixel_coords": [
        77,
        156,
        10.278192520141602
      ],
      "index": 1,
      "color": "green",
      "material": "poliigonmetalcorrugatedironsheet002"
    }
  ],
  "relationships": {
    "behind": [
      []
    ],
    "front": [
      []
    ],
    "left": [
      []
    ],
    "right": [
      []
    ]
  },
  "mask_filename": "CLEVRTEX_single_000446_flat.png",
  "normal_filename": "CLEVRTEX_single_000446_normal_0001.png",
  "albedo_filename": "CLEVRTEX_single_000446_albedo_0001.png",
  "depth_filename": "CLEVRTEX_single_000446_depth_0001.png",
  "shadow_filename": "CLEVRTEX_single_000446_shadow_0001.png"
}