{
  "num_objects": 1,
  "split": "single",
  "image_index": 298,
  "image_filename": "CLEVRTEX_single_000298.png",
  "ground_material": "poliigonfabricleatherbuffalorustic001",
  "directions": {
    "behind": [
      -0.761375367641449,
      0.6483114361763,
      0.0
    ],
    "front": [
      0.761375367641449,
      -0.6483114361763,
      -0.0
    ],
    "left": [
      -0.6483113765716553,
      -0.761375367641449,
      0.0
    ],
    "right": [
      0.6483113765716553,
      0.761375367641449,
      -0.0
    ],
    "above": [
      0.0,
      0.0,
      1.0
    ],
    "below": [
      -0.0,
      -0.0,
      -1.0
    ]
  },
  "objects": [
    {
      "shape": "monkey",
      "rotation": 127.13783275550732,
      "size": "medium",
      "3d_coords": [
        1.8423256874084473,
        2.044851064682007,
        0.6000000238418579
      ],
      "pixel_coords": [
        373,
        136,
        10.826943397521973
      ],
      "index": 1,
      "color": "brown",
      "material": "poliigonfabricrope001"
    }
  ],
  "relationships": {
    "behind": [
      []
    ],
    "front": [
      []
    ],
    "left": [
      []
    ],
    "right": [
      []
    ]
  },
  "mask_filename": "CLEVRTEX_single_000298_flat.png",
  "normal_filename": "CLEVRTEX_single_000298_normal_0001.png",
  "albedo_filename": "CLEVRTEX_single_000298_albedo_0001.png",
  "depth_filename": "CLEVRTEX_single_000298_depth_0001.png",
  "shadow_filename": "CLEVRTEX_single_000298_shadow_0001.png"
}