{
  "num_objects": 1,
  "split": "single",
  "image_index": 38,
  "image_filename": "CLEVRTEX_single_000038.png",
  "ground_material": "poliigonbricksflemishred001",
  "directions": {
    "behind": [
      -0.749523937702179,
      0.6619772911071777,
      0.0
    ],
    "front": [
      0.749523937702179,
      -0.6619772911071777,
      -0.0
    ],
    "left": [
      -0.6619772911071777,
      -0.7495238780975342,
      0.0
    ],
    "right": [
      0.6619772911071777,
      0.7495238780975342,
      -0.0
    ],
    "above": [
      0.0,
      0.0,
      1.0
    ],
    "below": [
      -0.0,
      -0.0,
      -1.0
    ]
  },
  "objects": [
    {
      "shape": "cube",
      "rotation": 164.91765279215034,
      "size": "large",
      "3d_coords": [
        -2.3184866905212402,
        1.0168157815933228,
        0.6363961100578308
      ],
      "pixel_coords": [
        208,
        90,
        12.586756706237793
      ],
      "index": 1,
      "color": "purple",
      "material": "poliigoninteriordesignrugstarrynight001"
    }
  ],
  "relationships": {
    "behind": [
      []
    ],
    "front": [
      []
    ],
    "left": [
      []
    ],
    "right": [
      []
    ]
  },
  "mask_filename": "CLEVRTEX_single_000038_flat.png",
  "normal_filename": "CLEVRTEX_single_000038_normal_0001.png",
  "albedo_filename": "CLEVRTEX_single_000038_albedo_0001.png",
  "depth_filename": "CLEVRTEX_single_000038_depth_0001.png",
  "shadow_filename": "CLEVRTEX_single_000038_shadow_0001.png"
}