{
  "num_objects": 1,
  "split": "single",
  "image_index": 371,
  "image_filename": "CLEVRTEX_single_000371.png",
  "ground_material": "poliigonmarble062",
  "directions": {
    "behind": [
      -0.7425949573516846,
      0.6697407960891724,
      0.0
    ],
    "front": [
      0.7425949573516846,
      -0.6697407960891724,
      -0.0
    ],
    "left": [
      -0.6697408556938171,
      -0.7425949573516846,
      0.0
    ],
    "right": [
      0.6697408556938171,
      0.7425949573516846,
      -0.0
    ],
    "above": [
      0.0,
      0.0,
      0.9999999403953552
    ],
    "below": [
      -0.0,
      -0.0,
      -0.9999999403953552
    ]
  },
  "objects": [
    {
      "shape": "sphere",
      "rotation": 98.46340477024282,
      "size": "small",
      "3d_coords": [
        -0.6613518595695496,
        0.01550607942044735,
        0.4000000059604645
      ],
      "pixel_coords": [
        221,
        134,
        12.059671401977539
      ],
      "index": 1,
      "color": "yellow",
      "material": "poliigoncliffjagged004"
    }
  ],
  "relationships": {
    "behind": [
      []
    ],
    "front": [
      []
    ],
    "left": [
      []
    ],
    "right": [
      []
    ]
  },
  "mask_filename": "CLEVRTEX_single_000371_flat.png",
  "normal_filename": "CLEVRTEX_single_000371_normal_0001.png",
  "albedo_filename": "CLEVRTEX_single_000371_albedo_0001.png",
  "depth_filename": "CLEVRTEX_single_000371_depth_0001.png",
  "shadow_filename": "CLEVRTEX_single_000371_shadow_0001.png"
}